README.md
setup.cfg
setup.py
neuro_fuzzy_matrix/__init__.py
neuro_fuzzy_matrix/test.py
neuro_fuzzy_matrix/tests_save.py
neuro_fuzzy_matrix.egg-info/PKG-INFO
neuro_fuzzy_matrix.egg-info/SOURCES.txt
neuro_fuzzy_matrix.egg-info/dependency_links.txt
neuro_fuzzy_matrix.egg-info/not-zip-safe
neuro_fuzzy_matrix.egg-info/top_level.txt