Metadata-Version: 2.1
Name: neuro-fuzzy-matrix
Version: 1.0
Summary: neuro fuzzy matrix
Author-email: epishina.nata@bk.ru
